dailyrevenue/__init__.py
dailyrevenue/dailyrevenue.py
testingdavid-1.0.dist-info/METADATA
testingdavid-1.0.dist-info/WHEEL
testingdavid-1.0.dist-info/top_level.txt
testingdavid-1.0.dist-info/RECORD
